setup.cfg
setup.py
commonsharedclasses/CosmosLogConfiguration.py
commonsharedclasses/DynamicCosmosRetrieve.py
commonsharedclasses/__init__.py
commonsharedclasses/blob_service_connection.py
commonsharedclasses/cosmos_connection.py
commonsharedclasses/cosmos_utility.py
commonsharedclasses/databricks_sql.py
commonsharedclasses/fetch_details.py
commonsharedclasses/service_principal_access_provider.py
commonsharedclasses/service_principal_authorization_provider.py
commonsharedclasses/singleton.py
commonsharedclasses/singleton_blob_service_client.py
commonsharedclasses/singleton_cluster_thrift_connection.py
commonsharedclasses/singleton_cosmos_client.py
commonsharedclasses/sql_query_provider.py
commonsharedclasses/tenant_lakehouse_query.py
commonsharedclasses.egg-info/PKG-INFO
commonsharedclasses.egg-info/SOURCES.txt
commonsharedclasses.egg-info/dependency_links.txt
commonsharedclasses.egg-info/not-zip-safe
commonsharedclasses.egg-info/top_level.txt