Metadata-Version: 2.1
Name: commonsharedclasses
Version: 0.0.20
Summary: This package will contain all common classes, version 0.0.20 updates:- Added funcURL and response logging in dynamiccosmosretrieve
Home-page: UNKNOWN
Author: Ankit Kumar
License: UNKNOWN
Platform: UNKNOWN
